{"GUID":"653873E5-43EC-400C-AE1C-2B106776186F","Objects":[{"1":{"m_objects":[2,6],"type":"64CB643F-2C9C-4857-AA01-4F6F995A4CBE"}},{"2":{"m_childrens":[],"m_components":[3,4,5],"m_parentGameObject":-1,"type":"764220D9-31E0-448B-9612-79A47B570367"}},{"3":{"m_Rotation":{"pitch":1.6820991039276123,"roll":-2.702588252699785e-36,"yaw":-244.8999481201172},"m_Scaling":{"x":0.981,"y":1.0,"z":1.0},"m_Translation":{"x":0.0,"y":0.0,"z":0.08898598700761795},"m_owner":2,"type":"57B43954-87AF-495A-8B58-E15890E621D1"}},{"4":{"m_owner":2,"m_staticMeshAsset":"8845238D-3716-454F-B4C2-CB1239EB9CF2","type":"303B0EAC-B07E-42E1-B6E9-A56F00E75814"}},{"5":{"m_albedo":{"a":1.0,"b":1.0,"g":0.800000011920929,"r":1.0},"m_albedoTexture":"3D976F90-867E-40B8-A31C-66B27C749E4F","m_ao":0.0,"m_metallic":0.05000000074505806,"m_owner":2,"m_roughness":0.10000000149011612,"type":"5B3EA494-8F58-4A28-A623-CCF822CDF3A1"}},{"6":{"m_childrens":[],"m_components":[7,8],"m_parentGameObject":-1,"type":"764220D9-31E0-448B-9612-79A47B570367"}},{"7":{"m_Rotation":{"pitch":1.875,"roll":0.0,"yaw":0.0},"m_Scaling":{"x":1.0,"y":1.0,"z":1.0},"m_Translation":{"x":0.0,"y":0.0,"z":10.0},"m_owner":6,"type":"57B43954-87AF-495A-8B58-E15890E621D1"}},{"8":{"m_lightColor":{"a":1.0,"b":0.47456198930740356,"g":0.4860050082206726,"r":1.335433006286621},"m_lightPosition":{"w":1.0,"x":0.0,"y":0.0,"z":-10.0},"m_owner":6,"type":"3EF471CA-C9A2-4F2B-AEA9-326276AE4763"}}],"Version":"1.000000"}